{
  "$fillAlpha": 0.5,

  "$inputTypeModeTitleColor": [1.0, 1.0, 1.0],
  "$inputTypeModeSubtitleColor": [0.848, 0.848, 0.848],

  "$percentFontType": "default",
  "$percentFontSize": 1.0,
  "$percentOffset": [0, 0],
  "$percentTextAlpha": 1.0,
  "$percentTextColor": [1.0, 1.0, 1.0],
  "$percentTextLayer": 2,
  "$percentTextShadow": true,
  "$percentVisible": true,

  "$showNotesMsgPanel": true,
  "$notesMsgTextboxSize": ["100%", 36],

  "$menuCreatorVersion": "Thony Ui v1.2.4",

  "$quickLootCommonIgnored": true,
  "$quickLootOnTextColor": [0.10, 0.66, 0.10],
  "$quickLootOffTextColor": [0.80, 0.06, 0.06]
}